<MTConnectDevices>
  <Devices>
    <Device uuid="IVAC" id="ivac" name="iVAC-System">

      <!-- General information -->
      <Description>
         Device for iVAC system.
      </Description>
      <DataItems>
        <DataItem category="EVENT" id="avail" name="avail" type="AVAILABILITY"/>
        <DataItem category="EVENT" id="A1ToolPlus" type="EQUIPMENT_MODE" subType="POWERED"/>
        <DataItem category="EVENT" id="A2ToolPlus" type="EQUIPMENT_MODE" subType="POWERED"/>
        <DataItem category="EVENT" id="SimulationMode" type="EXECUTION"/>
        <DataItem category="CONDITION" id="ivac_tools_status" type="SYSTEM"/>
        <DataItem category="CONDITION" id="Buzzer" type="SYSTEM"/>
      </DataItems>
    </Device>
  </Devices>
</MTConnectDevices>